typetreegeneratorapiex-0.0.9.data/purelib/TypeTreeGeneratorAPI/TypeTreeGenerator.py
typetreegeneratorapiex-0.0.9.data/purelib/TypeTreeGeneratorAPI/__init__.py
typetreegeneratorapiex-0.0.9.data/purelib/TypeTreeGeneratorAPI/libTypeTreeGeneratorAPI.dylib
typetreegeneratorapiex-0.0.9.data/purelib/TypeTreeGeneratorAPI/libcapstone.dylib
typetreegeneratorapiex-0.0.9.dist-info/licenses/LICENSE
typetreegeneratorapiex-0.0.9.dist-info/METADATA
typetreegeneratorapiex-0.0.9.dist-info/WHEEL
typetreegeneratorapiex-0.0.9.dist-info/top_level.txt
typetreegeneratorapiex-0.0.9.dist-info/RECORD
