Metadata-Version: 2.4
Name: TypeTreeGeneratorAPIEx
Version: 0.0.9
Summary: Mod builds of TypeTreeGeneratorAPI
Author-email: mos9527 <greats3an@gmail.com>
License: MIT License
Requires-Python: >=3.7
License-File: LICENSE
Provides-Extra: dev
Requires-Dist: ruff; extra == "dev"
Dynamic: license-file
